LICENSE
MANIFEST.in
README.md
pyproject.toml
setup.cfg
setup.py
src/kLoop.egg-info/PKG-INFO
src/kLoop.egg-info/SOURCES.txt
src/kLoop.egg-info/dependency_links.txt
src/kLoop.egg-info/top_level.txt
src/kloop/__init__.py
src/kloop/ktls.pxd
src/kloop/ktls.pyx
src/kloop/uring.pxd
src/kloop/uring.pyx
tests/test_loop.py